{
  "paper_id": "pa-13-logical-framework",
  "series": "Proof-Architecture",
  "bundle": "\\\\dlowenas\\brain\\Backside\\stations\\axioms.station\\03_FINAL_READY\\Proof-Architecture\\pa-13-logical-framework",
  "source_json": "\\\\dlowenas\\brain\\Backside\\stations\\axioms.station\\03_FINAL_READY\\Proof-Architecture\\pa-13-logical-framework\\JSON\\pa-13-logical-framework.paper-grade.json",
  "generated_at": "2026-06-03T08:04:00",
  "verdict": "NEEDS_RIGOR",
  "claim_count": 0,
  "failing_claim_count": 0,
  "formal_marker_count": 0,
  "failure_counts": {},
  "claim_results": []
}