{
  "paper_id": "index",
  "source_file": "\\\\dlowenas\\brain\\axioms\\00_INBOX_DROP_PAPERS_HERE\\index.md",
  "generated_at": "2026-05-11T18:08:43",
  "metrics": {
    "word_count": 414,
    "section_count": 2,
    "equation_count": 1,
    "claim_candidate_count": 0,
    "top_terms": "px-6, flex, items-center, font-sans, font-medium, html, rounded-lg, group, w-10, font-mono, flex-1, card-number, text-2xl, font-bold, text-right"
  },
  "sections": [
    {
      "title": "Document Start",
      "text": ":::::::::::::::::::::: {.max-w-5xl .mx-auto .px-6 .pb-24 role=\"main\"}\n::: {.section .mb-12}\n[ [Bundle Viewer]{.font-sans .font-medium .text-gray-300 .group-hover:text-white .transition-colors} ](pa-00-bundle-viewer.html){.utility-link .rounded-lg .px-6 .py-4 .flex .items-center .gap-4 .group .inline-flex .w-full .md:w-auto}\n:::\n:::::::::::::::::::: {.section .mb-16}\n::::: {.flex .items-center .gap-4 .mb-10}\n::: {.w-10 .h-px .bg-accent}\n:::"
    },
    {
      "title": "The Proof Layers {#the-proof-layers .section-label .uppercase .text-sm .font-mono .text-accent .tracking-widest}",
      "text": "::: {.flex-1 .h-px .bg-gradient-to-r .from-accent/20 .to-transparent}\n:::\n:::::\n:::::::::::::::: {.grid .gap-3}\n[[01]{.card-number .font-mono .text-2xl .font-bold .w-10 .text-right}](pa-01-unavoidable-conclusion.html){.series-card .rounded-lg .px-6 .py-5 .flex .items-center .gap-5 .group}\n::: {.w-px .h-8 .bg-gray-800}\n:::\n[The Unavoidable Conclusion]{.card-title .font-sans .text-lg .font-medium .flex-1} [[02]{.card-number .font-mono .text-2xl .font-bold .w-10 .text-right}](pa-02-foundation.html){.series-card .rounded-lg .px-6 .py-5 .flex .items-center .gap-5 .group}\n::: {.w-px .h-8 .bg-gray-800}\n:::\n[Foundation Spine]{.card-title .font-sans .text-lg .font-medium .flex-1} [[03]{.card-number .font-mono .text-2xl .font-bold .w-10 .text-right}](pa-03-ontological-tree.html){.series-card .rounded-lg .px-6 .py-5 .flex .items-center .gap-5 .group}\n::: {.w-px .h-8 .bg-gray-800}\n:::\n[The Ontological Decision Tree]{.card-title .font-sans .text-lg .font-medium .flex-1} [[04]{.card-number .font-mono .text-2xl .font-bold .w-10 .text-right}](pa-04-bifurcation.html){.series-card .rounded-lg .px-6 .py-5 .flex .items-center .gap-5 .group}\n::: {.w-px .h-8 .bg-gray-800}\n:::\n[Bifurcation Chamber]{.card-title .font-sans .text-lg .font-medium .flex-1} [[05]{.card-number .font-mono .text-2xl .font-bold .w-10 .text-right}](pa-05-structural-isomorphism.html){.series-card .rounded-lg .px-6 .py-5 .flex .items-center .gap-5 .group}\n::: {.w-px .h-8 .bg-gray-800}\n:::\n[Structural Isomorphism]{.card-title .font-sans .text-lg .font-medium .flex-1} [[06]{.card-number .font-mono .text-2xl .font-bold .w-10 .text-right}](pa-06-subsystems.html){.series-card .rounded-lg .px-6 .py-5 .flex .items-center .gap-5 .group}\n::: {.w-px .h-8 .bg-gray-800}\n:::\n[Five Paired Subsystems]{.card-title .font-sans .text-lg .font-medium .flex-1} [[07]{.card-number .font-mono .text-2xl .font-bold .w-10 .text-right}](pa-07-closure.html){.series-card .rounded-lg .px-6 .py-5 .flex .items-center .gap-5 .group}\n::: {.w-px .h-8 .bg-gray-800}\n:::\n[Closure Layer]{.card-title .font-sans .text-lg .font-medium .flex-1} [[08]{.card-number .font-mono .text-2xl .font-bold .w-10 .text-right}](pa-08-falsification.html){.series-card .rounded-lg .px-6 .py-5 .flex .items-center .gap-5 .group}\n::: {.w-px .h-8 .bg-gray-800}\n:::\n[Falsification Court]{.card-title .font-sans .text-lg .font-medium .flex-1} [[09]{.card-number .font-mono .text-2xl .font-bold .w-10 .text-right}](pa-09-propagation-map.html){.series-card .rounded-lg .px-6 .py-5 .flex .items-center .gap-5 .group}\n::: {.w-px .h-8 .bg-gray-800}\n:::\n[Substrate Propagation Map]{.card-title .font-sans .text-lg .font-medium .flex-1} [[10]{.card-number .font-mono .text-2xl .font-bold .w-10 .text-right}](pa-10-evidence.html){.series-card .rounded-lg .px-6 .py-5 .flex .items-center .gap-5 .group}\n::: {.w-px .h-8 .bg-gray-800}\n:::\n[Convergence and Evidence]{.card-title .font-sans .text-lg .font-medium .flex-1} [[11]{.card-number .font-mono .text-2xl .font-bold .w-10 .text-right}](pa-11-testable-predictions.html){.series-card .rounded-lg .px-6 .py-5 .flex .items-center .gap-5 .group}\n::: {.w-px .h-8 .bg-gray-800}\n:::\n[Testable Predictions]{.card-title .font-sans .text-lg .font-medium .flex-1} [[12]{.card-number .font-mono .text-2xl .font-bold .w-10 .text-right}](pa-12-proof-explorer.html){.series-card .rounded-lg .px-6 .py-5 .flex .items-center .gap-5 .group}\n::: {.w-px .h-8 .bg-gray-800}\n:::\n[Proof Explorer]{.card-title .font-sans .text-lg .font-medium .flex-1} [[13]{.card-number .font-mono .text-2xl .font-bold .w-10 .text-right}](pa-15-logical-framework.html){.series-card .rounded-lg .px-6 .py-5 .flex .items-center .gap-5 .group}\n::: {.w-px .h-8 .bg-gray-800}\n:::\n[Logical Framework]{.card-title .font-sans .text-lg .font-medium .flex-1}\n::::::::::::::::\n::::::::::::::::::::\n::::::::::::::::::::::"
    }
  ],
  "equations": [
    ":::::::::::::::::::::: {.max-w-5xl .mx-auto .px-6 .pb-24 role=\"main\"}"
  ],
  "claims": []
}